wrd/__init__.py
wrd/__main__.py
wrd-1.0.3.dist-info/licenses/LICENSE
wrd-1.0.3.dist-info/METADATA
wrd-1.0.3.dist-info/WHEEL
wrd-1.0.3.dist-info/entry_points.txt
wrd-1.0.3.dist-info/top_level.txt
wrd-1.0.3.dist-info/RECORD
