Metadata-Version: 2.4
Name: wrd
Version: 1.0.3
Summary: WRD (Word) - Narzędzie workflow dla Claude Code na Fedorze
Home-page: https://github.com/wronai/wrd
Author: Claude Code User
Author-email: Tom Sapletta <info@softreck.dev>
License: MIT
Project-URL: homepage, https://github.com/wronai/wrd
Project-URL: repository, https://github.com/wronai/wrd
Project-URL: documentation, https://github.com/wronai/wrd#readme
Project-URL: Bug Tracker, https://github.com/wronai/wrd/issues
Classifier: Development Status :: 4 - Beta
Classifier: Intended Audience :: Developers
Classifier: Topic :: Software Development :: Build Tools
Classifier: License :: OSI Approved :: MIT License
Classifier: Programming Language :: Python :: 3
Classifier: Programming Language :: Python :: 3.8
Classifier: Programming Language :: Python :: 3.9
Classifier: Programming Language :: Python :: 3.10
Classifier: Programming Language :: Python :: 3.11
Classifier: Operating System :: POSIX :: Linux
Requires-Python: >=3.8
License-File: LICENSE
Requires-Dist: click>=8.0.0
Requires-Dist: rich>=12.0.0
Requires-Dist: pydantic>=1.9.0
Requires-Dist: python-dotenv>=0.19.0
Requires-Dist: requests>=2.28.0
Provides-Extra: test
Requires-Dist: pytest>=7.0.0; extra == "test"
Requires-Dist: pytest-cov>=3.0.0; extra == "test"
Requires-Dist: pytest-mock>=3.0.0; extra == "test"
Provides-Extra: dev
Requires-Dist: black>=22.0.0; extra == "dev"
Requires-Dist: flake8>=4.0.0; extra == "dev"
Requires-Dist: mypy>=0.950; extra == "dev"
Requires-Dist: pytest>=7.0.0; extra == "dev"
Requires-Dist: pytest-cov>=3.0.0; extra == "dev"
Requires-Dist: pytest-mock>=3.0.0; extra == "dev"
Provides-Extra: data
Requires-Dist: pandas>=1.5.0; extra == "data"
Requires-Dist: numpy>=1.24.0; extra == "data"
Requires-Dist: matplotlib>=3.6.0; extra == "data"
Provides-Extra: web
Requires-Dist: fastapi>=0.95.0; extra == "web"
Requires-Dist: uvicorn>=0.20.0; extra == "web"
Dynamic: author
Dynamic: home-page
Dynamic: license-file
Dynamic: requires-python
